total_points_model/__init__.py
total_points_model/config.py
total_points_model/domain/__init__.py
total_points_model/domain/contracts/__init__.py
total_points_model/domain/contracts/mappings.py
total_points_model/domain/contracts/modelling_data_contract.py
total_points_model/domain/contracts/rolling_columns.py
total_points_model/domain/modelling/__init__.py
total_points_model/domain/modelling/hyperparameter_tuning.py
total_points_model/domain/modelling/model_evaluation.py
total_points_model/domain/modelling/optuna_xgb_param_grid.py
total_points_model/domain/modelling/supermodel.py
total_points_model/domain/preprocessing/__init__.py
total_points_model/domain/preprocessing/data_preprocessor.py
total_points_model/domain/preprocessing/elo_calculator.py
total_points_model/domain/preprocessing/preprocessing_functions.py
total_points_model-1.0.5.dist-info/LICENSE
total_points_model-1.0.5.dist-info/METADATA
total_points_model-1.0.5.dist-info/WHEEL
total_points_model-1.0.5.dist-info/top_level.txt
total_points_model-1.0.5.dist-info/RECORD
