Metadata-Version: 2.1
Name: total-points-model
Version: 1.0.5
Summary: Train an AFL Total Points model
Author-email: Ciaran Grant <ciaran.grant@hotmail.co.uk>
License: MIT License
Project-URL: Homepage, https://github.com/ciaran-grant/afl-total-points-model
Requires-Python: >=3.9
License-File: LICENSE
Requires-Dist: pandas (==1.5.3)
Requires-Dist: numpy (==1.23.5)
Requires-Dist: optuna (==3.1.1)
Requires-Dist: xgboost (==1.7.3)
Requires-Dist: scikit-learn (==1.2.2)
Requires-Dist: seaborn (==0.12.2)
Requires-Dist: matplotlib (==3.7.1)
Requires-Dist: shap (==0.41.0)
Requires-Dist: joblib (==1.1.1)
Requires-Dist: plotly (==5.14.1)
Requires-Dist: notebook (==6.5.3)
Requires-Dist: jupyter (==1.0.0)
Requires-Dist: jupyter-server (==1.23.4)
Requires-Dist: nbclient (==0.5.13)
Requires-Dist: matplotlib-inline (==0.1.6)
Provides-Extra: dev
Requires-Dist: pytest ; extra == 'dev'
